dashboard/__init__.py
dashboard/dashboard.py
MicroPython_Dashboard_carlsonrocco-0.0.1.dist-info/LICENSE.txt
MicroPython_Dashboard_carlsonrocco-0.0.1.dist-info/METADATA
MicroPython_Dashboard_carlsonrocco-0.0.1.dist-info/WHEEL
MicroPython_Dashboard_carlsonrocco-0.0.1.dist-info/top_level.txt
MicroPython_Dashboard_carlsonrocco-0.0.1.dist-info/RECORD
