Metadata-Version: 2.1
Name: MicroPython-Dashboard-carlsonrocco
Version: 0.0.1
Summary: A modular dashboard made using WS2812b individually addressable LEDs and an ESP8266 microcontroller running MicroPython
Home-page: UNKNOWN
Author: Rocco Carlson
Author-email: rocstrrr@gmail.com
License: UNKNOWN
Platform: UNKNOWN
Classifier: Programming Language :: Python :: 3
Classifier: License :: OSI Approved :: MIT License
Classifier: Operating System :: OS Independent
Requires-Python: >=3.6
